{
	"name": "ds13",
	"properties": {
		"linkedServiceName": {
			"referenceName": "AzureBlobStorage1",
			"type": "LinkedServiceReference"
		},
		"parameters": {
			"file_name": {
				"type": "String"
			}
		},
		"annotations": [],
		"type": "DelimitedText",
		"typeProperties": {
			"location": {
				"type": "AzureBlobStorageLocation",
				"fileName": {
					"value": "@dataset().file_name",
					"type": "Expression"
				},
				"folderPath": "input",
				"container": "files"
			},
			"columnDelimiter": ",",
			"escapeChar": "\\",
			"firstRowAsHeader": true,
			"quoteChar": "\""
		},
		"schema": [
			{
				"name": "customer_id",
				"type": "String"
			},
			{
				"name": "first_Name",
				"type": "String"
			},
			{
				"name": "last_Name",
				"type": "String"
			},
			{
				"name": "city",
				"type": "String"
			},
			{
				"name": "dob",
				"type": "String"
			},
			{
				"name": "enrollment_date",
				"type": "String"
			},
			{
				"name": "pan_card",
				"type": "String"
			}
		]
	},
	"type": "Microsoft.DataFactory/factories/datasets"
}